superconf18_midibadge/__init__.py
superconf18_midibadge/midistuff.py
superconf18_midibadge/tools/__init__.py
superconf18_midibadge/tools/midi2basic.py
superconf18_midibadge/tools/midi3track.py
superconf18_midibadge/tools/midiinfo.py
superconf18_midibadge/tools/midisplit.py
superconf18_midibadge/uistuff.py
superconf18_midibadge-0.2.0.dist-info/entry_points.txt
superconf18_midibadge-0.2.0.dist-info/LICENSE
superconf18_midibadge-0.2.0.dist-info/WHEEL
superconf18_midibadge-0.2.0.dist-info/METADATA
superconf18_midibadge-0.2.0.dist-info/RECORD
