Metadata-Version: 2.1
Name: superconf18-midibadge
Version: 0.2.0
Summary: Generate Basic code for the Hackaday Superconf 2018 Badge from a MIDI file
Home-page: https://github.com/jonemo/superconf18-midibadge
License: MIT
Keywords: badgelife,superconference
Author: Jonas Neubert
Author-email: jn@jonasneubert.com
Requires-Python: >=3.6,<4.0
Classifier: License :: OSI Approved :: MIT License
Classifier: Programming Language :: Python :: 3
Classifier: Programming Language :: Python :: 3.6
Classifier: Programming Language :: Python :: 3.7
Requires-Dist: midi
Requires-Dist: toml (>=0.9,<0.10)
Project-URL: Repository, https://github.com/jonemo/superconf18-midibadge
